krllint/__init__.py
krllint/__main__.py
krllint/config.py
krllint/linter.py
krllint/parameters.py
krllint/reporter.py
krllint/rules.py
krllint/tools.py
krllint-0.1.8.dist-info/METADATA
krllint-0.1.8.dist-info/RECORD
krllint-0.1.8.dist-info/WHEEL
krllint-0.1.8.dist-info/entry_points.txt
krllint-0.1.8.dist-info/top_level.txt
