Metadata-Version: 2.1
Name: krllint
Version: 0.1.8
Summary: KRL code checker
Home-page: https://github.com/d4nuu8/krllint
Author: Daniel Braunwarth
Author-email: d4nuu8@gmail.com
License: MIT
Platform: UNKNOWN
Classifier: Development Status :: 3 - Alpha
Classifier: License :: OSI Approved :: MIT License
Classifier: Environment :: Console
Classifier: Intended Audience :: Developers
Classifier: Topic :: Software Development :: Quality Assurance
Classifier: Operating System :: OS Independent
Classifier: Programming Language :: Python :: 3 :: Only
Classifier: Programming Language :: Python :: 3.5
Requires-Python: >=3.5
Requires-Dist: colorama
